dbt2looker/__init__.py
dbt2looker/cli.py
dbt2looker/generator.py
dbt2looker/models.py
dbt2looker/parser.py
dbt2looker-0.11.0.dist-info/entry_points.txt
dbt2looker-0.11.0.dist-info/LICENSE
dbt2looker-0.11.0.dist-info/WHEEL
dbt2looker-0.11.0.dist-info/METADATA
dbt2looker-0.11.0.dist-info/RECORD
