Metadata-Version: 2.1
Name: dbt2looker
Version: 0.11.0
Summary: Generate lookml view files from dbt models
Home-page: https://github.com/hubble-data/dbt2looker
License: MIT
Author: oliverlaslett
Author-email: oliver@gethubble.io
Requires-Python: >=3.7
Classifier: License :: OSI Approved :: MIT License
Classifier: Programming Language :: Python :: 3
Classifier: Programming Language :: Python :: 3.10
Classifier: Programming Language :: Python :: 3.7
Classifier: Programming Language :: Python :: 3.8
Classifier: Programming Language :: Python :: 3.9
Requires-Dist: PyYAML (>=5)
Requires-Dist: importlib-metadata (>=4)
Requires-Dist: lkml (>=1.1)
Requires-Dist: pydantic (>=1.8)
Requires-Dist: typing-extensions (>=4.0)
Project-URL: Repository, https://github.com/hubble-data/dbt2looker
